{     
  "Changes": 
  [
    {
          
      "Action": "EditData",
      "Target": "Characters/Dialogue/Seba",
      "Entries": 
      {
        // ESPECIAIS
        "Introduction": "{{i18n:Seba.Dialogue.Introduction}}",
        "MovieInvitation": "{{i18n:Seba.Dialogue.MovieInvitation}}",

        // RESORT
        "Resort_Entering": "{{i18n:Seba.Dialogue.Resort_Entering}}",
        "Resort_Leaving": "{{i18n:Seba.Dialogue.Resort_Leaving}}",
        "Resort_Shore": "{{i18n:Seba.Dialogue.Resort_Shore}}",
        "Resort_Shore_2": "{{i18n:Seba.Dialogue.Resort_Shore_2}}",
        "Resort_Umbrella": "{{i18n:Seba.Dialogue.Resort_Umbrella}}",
        "Resort_Wander": "{{i18n:Seba.Dialogue.Resort_Wander}}",
        "Resort_Bar": "{{i18n:Seba.Dialogue.Resort_Bar}}",
        "Resort": "{{i18n:Seba.Dialogue.Resort}}",

        // DIALOGO COMUM
        //segunda-feira
        "Mon": "{{i18n:Seba.Dialogue.Mon}}",
        "Mon2": "{{i18n:Seba.Dialogue.Mon2}}",
        "Mon4": "{{i18n:Seba.Dialogue.Mon4}}",
        "Mon6": "{{i18n:Seba.Dialogue.Mon6}}",
        "Mon8": "{{i18n:Seba.Dialogue.Mon8}}",
        "Mon10": "{{i18n:Seba.Dialogue.Mon10}}",

        //terça-feira
        "Tue": "{{i18n:Seba.Dialogue.Tue}}",
        "Tue2": "{{i18n:Seba.Dialogue.Tue2}}",
        "Tue4": "{{i18n:Seba.Dialogue.Tue4}}",
        "Tue6": "{{i18n:Seba.Dialogue.Tue6}}",
        "Tue8": "{{i18n:Seba.Dialogue.Tue8}}",
        "Tue10": "{{i18n:Seba.Dialogue.Tue10}}",

        //quarta-feira
        "Wed": "{{i18n:Seba.Dialogue.Wed}}",
        "Wed2": "{{i18n:Seba.Dialogue.Wed2}}",
        "Wed4": "{{i18n:Seba.Dialogue.Wed4}}",
        "Wed6": "{{i18n:Seba.Dialogue.Wed6}}",
        "Wed8": "{{i18n:Seba.Dialogue.Wed8}}",
        "Wed10": "{{i18n:Seba.Dialogue.Wed10}}",

        //quinta-feira
        "Thu": "{{i18n:Seba.Dialogue.Thu}}",
        "Thu2": "{{i18n:Seba.Dialogue.Thu2}}",
        "Thu4": "{{i18n:Seba.Dialogue.Thu4}}",
        "Thu6": "{{i18n:Seba.Dialogue.Thu6}}",
        "Thu8": "{{i18n:Seba.Dialogue.Thu8}}",
        "Thu10": "{{i18n:Seba.Dialogue.Thu10}}",

        //sexta-feira
        "Fri": "{{i18n:Seba.Dialogue.Fri}}",
        "Fri2": "{{i18n:Seba.Dialogue.Fri2}}",
        "Fri4": "{{i18n:Seba.Dialogue.Fri4}}",
        "Fri6": "{{i18n:Seba.Dialogue.Fri6}}",
        "Fri8": "{{i18n:Seba.Dialogue.Fri8}}",
        "Fri10": "{{i18n:Seba.Dialogue.Fri10}}",

        //sabado
        "Sat": "{{i18n:Seba.Dialogue.Sat}}",
        "Sat2": "{{i18n:Seba.Dialogue.Sat2}}",
        "Sat4": "{{i18n:Seba.Dialogue.Sat4}}",
        "Sat6": "{{i18n:Seba.Dialogue.Sat6}}",
        "Sat8": "{{i18n:Seba.Dialogue.Sat8}}",
        "Sat10": "{{i18n:Seba.Dialogue.Sat10}}",

        //domingo
        "Sun": "{{i18n:Seba.Dialogue.Sun}}",
        "Sun2": "{{i18n:Seba.Dialogue.Sun2}}",
        "Sun4": "{{i18n:Seba.Dialogue.Sun4}}",
        "Sun6": "{{i18n:Seba.Dialogue.Sun6}}",
        "Sun8": "{{i18n:Seba.Dialogue.Sun8}}",
        "Sun10": "{{i18n:Seba.Dialogue.Sun10}}",

        // FESTIVAIS

        //Egg Festival
        "spring_13": "{{i18n:Seba.Dialogue.spring_13}}",
        //Flower Dance
        "spring_24": "{{i18n:Seba.Dialogue.spring_24}}",
        //Luau
        "summer_11": "{{i18n:Seba.Dialogue.summer_11}}",
        //Dance of the Moonlight Jellies
        "summer_28": "{{i18n:Seba.Dialogue.summer_28}}",
        //Stardew Valley Fair
        "fall_16": "{{i18n:Seba.Dialogue.fall_16}}",
        //Spirit's Eve
        "fall_27": "{{i18n:Seba.Dialogue.fall_27}}",
        //Festival of Ice
        "winter_8": "{{i18n:Seba.Dialogue.winter_8}}",
        //Night Market
        "winter_15": "{{i18n:Seba.Dialogue.winter_15}}",
        //Feast of the Winter Star
        "winter_25": "{{i18n:Seba.Dialogue.winter_25}}",

        // PRIMAVERA
        "spring_1": "{{i18n:Seba.Dialogue.spring_1}}",

        // VERAO
        "summer_1": "{{i18n:Seba.Dialogue.summer_1}}",

        // OUTONO
        "fall_1": "{{i18n:Seba.Dialogue.fall_1}}",

        // INVERNO
        "winter_1": "{{i18n:Seba.Dialogue.winter_1}}",

        // EVENTO
        "Evento_Anime_Bom": "{{i18n:Seba.Dialogue.Evento_Anime_Bom}}",
        "Evento_Anime_Neutro": "{{i18n:Seba.Dialogue.Evento_Anime_Neutro}}",
        "Evento_Anime_Ruim": "{{i18n:Seba.Dialogue.Evento_Anime_Ruim}}"
      }
    }
  ]
}